pysaraf/__init__.py
pysaraf/hello.py
pysaraf/videocall.py
pysaraf-0.0.1.dist-info/LICENSE
pysaraf-0.0.1.dist-info/METADATA
pysaraf-0.0.1.dist-info/WHEEL
pysaraf-0.0.1.dist-info/top_level.txt
pysaraf-0.0.1.dist-info/RECORD
