Metadata-Version: 2.1
Name: pysaraf
Version: 0.0.1
Summary: for fun
Home-page: https://github.com/VaibhavSaraf/
Author: Vaibhav Saraf
Author-email: vaibhavgsaraf@gmail.com
License: UNKNOWN
Platform: UNKNOWN
Classifier: Programming Language :: Python :: 3
Classifier: License :: OSI Approved :: MIT License
Classifier: Operating System :: OS Independent
Requires-Python: >=3.6
